libdiamonds.dylib
pyDiamonds.cpython-36m-darwin.so
pyDiamonds-1.1.0.dist-info/LICENSE
pyDiamonds-1.1.0.dist-info/METADATA
pyDiamonds-1.1.0.dist-info/WHEEL
pyDiamonds-1.1.0.dist-info/top_level.txt
pyDiamonds-1.1.0.dist-info/RECORD
