Metadata-Version: 2.1
Name: pyDiamonds
Version: 1.1.0
Summary: A tool for bayesian parameter estimation and model selection
Home-page: UNKNOWN
Author: Enrico Corsaro, Joris de Ridder & Marco Müllner
Author-email: muellnermarco@gmail.com
License: UNKNOWN
Platform: UNKNOWN
